{"root":{"tags":null,"renderToIntermediateTexture":false,"maxLayoutCycle":3,"adaptHeightToChildren":false,"adaptWidthToChildren":false,"background":"","metadata":{"_previousCenter":{"x":1,"y":1}},"isHitTestVisible":true,"isPointerBlocker":false,"isFocusInvisible":false,"clipChildren":true,"clipContent":true,"useBitmapCache":false,"shadowOffsetX":0,"shadowOffsetY":0,"shadowBlur":0,"shadowColor":"black","hoverCursor":"","alpha":1,"scaleX":1,"scaleY":1,"rotation":0,"transformCenterY":0.5,"transformCenterX":0.5,"horizontalAlignment":2,"verticalAlignment":2,"fixedRatio":0,"width":"100%","height":"100%","color":"","zIndex":0,"notRenderable":false,"isVisible":true,"descendantsOnlyPadding":false,"paddingLeft":"0px","paddingRight":"0px","paddingTop":"0px","paddingBottom":"0px","left":"0px","top":"0px","linkOffsetX":"0px","linkOffsetY":"0px","isEnabled":true,"disabledColor":"#9a9a9a","disabledColorItem":"#6a6a6a","name":"root","className":"Container","children":[{"tags":["1:0","0:0"],"renderToIntermediateTexture":false,"maxLayoutCycle":3,"adaptHeightToChildren":false,"adaptWidthToChildren":false,"background":"","isHitTestVisible":true,"isPointerBlocker":true,"isFocusInvisible":false,"clipChildren":true,"clipContent":true,"useBitmapCache":false,"shadowOffsetX":0,"shadowOffsetY":0,"shadowBlur":0,"shadowColor":"black","hoverCursor":"","alpha":1,"scaleX":1,"scaleY":1,"rotation":0,"transformCenterY":0.5,"transformCenterX":0.5,"horizontalAlignment":2,"verticalAlignment":2,"fixedRatio":0,"width":"100%","height":"100%","color":"","zIndex":0,"notRenderable":false,"isVisible":true,"descendantsOnlyPadding":false,"paddingLeft":"0px","paddingRight":"0px","paddingTop":"0px","paddingBottom":"0px","left":"0px","top":"0px","linkOffsetX":"0px","linkOffsetY":"0px","isEnabled":true,"disabledColor":"#9a9a9a","disabledColorItem":"#6a6a6a","name":"Grid","className":"Grid","children":[{"tags":["2:0","1:0","0:0"],"renderToIntermediateTexture":false,"maxLayoutCycle":3,"adaptHeightToChildren":false,"adaptWidthToChildren":false,"background":"","isHitTestVisible":true,"isPointerBlocker":true,"isFocusInvisible":false,"clipChildren":true,"clipContent":true,"useBitmapCache":false,"shadowOffsetX":0,"shadowOffsetY":0,"shadowBlur":0,"shadowColor":"black","hoverCursor":"","alpha":1,"scaleX":1,"scaleY":1,"rotation":0,"transformCenterY":0.5,"transformCenterX":0.5,"horizontalAlignment":2,"verticalAlignment":2,"fixedRatio":0,"width":"100%","height":"100%","color":"","zIndex":0,"notRenderable":false,"isVisible":true,"descendantsOnlyPadding":false,"paddingLeft":"0px","paddingRight":"0px","paddingTop":"0px","paddingBottom":"0px","left":"0px","top":"0px","linkOffsetX":"0px","linkOffsetY":"0px","isEnabled":true,"disabledColor":"#9a9a9a","disabledColorItem":"#6a6a6a","name":"Grid","className":"Grid","children":[{"tags":["0:1"],"renderToIntermediateTexture":false,"maxLayoutCycle":3,"adaptHeightToChildren":false,"adaptWidthToChildren":false,"background":"","isHitTestVisible":true,"isPointerBlocker":true,"isFocusInvisible":false,"clipChildren":true,"clipContent":true,"useBitmapCache":false,"shadowOffsetX":0,"shadowOffsetY":0,"shadowBlur":0,"shadowColor":"black","hoverCursor":"","alpha":1,"scaleX":1,"scaleY":1,"rotation":0,"transformCenterY":0.5,"transformCenterX":0.5,"horizontalAlignment":2,"verticalAlignment":2,"fixedRatio":0,"width":"100%","height":"100%","color":"","zIndex":0,"notRenderable":false,"isVisible":true,"descendantsOnlyPadding":false,"paddingLeft":"0px","paddingRight":"0px","paddingTop":"0px","paddingBottom":"0px","left":"0px","top":"0px","linkOffsetX":"0px","linkOffsetY":"0px","isEnabled":true,"disabledColor":"#9a9a9a","disabledColorItem":"#6a6a6a","name":"Grid","className":"Grid","children":[{"tags":null,"thickness":1,"cornerRadius":0,"renderToIntermediateTexture":false,"maxLayoutCycle":3,"adaptHeightToChildren":false,"adaptWidthToChildren":false,"background":"#333333","isHitTestVisible":true,"isPointerBlocker":true,"isFocusInvisible":false,"clipChildren":true,"clipContent":true,"useBitmapCache":false,"shadowOffsetX":0,"shadowOffsetY":0,"shadowBlur":0,"shadowColor":"black","hoverCursor":"","fontOffset":{"ascent":90.5,"height":113.5,"descent":23},"alpha":1,"scaleX":1,"scaleY":1,"rotation":0,"transformCenterY":0.5,"transformCenterX":0.5,"horizontalAlignment":2,"verticalAlignment":2,"fixedRatio":0,"width":"644.76px","height":"131.19px","color":"#ffffff","zIndex":0,"notRenderable":false,"isVisible":true,"descendantsOnlyPadding":false,"paddingLeft":"0px","paddingRight":"0px","paddingTop":"0px","paddingBottom":"0px","left":"-2.11px","top":"45.23003605233081px","linkOffsetX":"0px","linkOffsetY":"0px","isEnabled":true,"disabledColor":"#9a9a9a","disabledColorItem":"#6a6a6a","name":"EndButton","className":"Button","fontFamily":"Arial","fontSize":"100px","fontWeight":"","fontStyle":"","children":[{"tags":null,"resizeToFit":false,"textWrapping":1,"text":"End","textHorizontalAlignment":2,"textVerticalAlignment":2,"lineSpacing":"0px","outlineWidth":0,"underline":false,"lineThrough":false,"outlineColor":"white","wordDivider":" ","isHitTestVisible":true,"isPointerBlocker":false,"isFocusInvisible":false,"clipChildren":true,"clipContent":true,"useBitmapCache":false,"shadowOffsetX":0,"shadowOffsetY":0,"shadowBlur":0,"shadowColor":"black","hoverCursor":"","fontOffset":{"ascent":90.5,"height":113.5,"descent":23},"alpha":1,"scaleX":1,"scaleY":1,"rotation":0,"transformCenterY":0.5,"transformCenterX":0.5,"horizontalAlignment":2,"verticalAlignment":2,"fixedRatio":0,"width":"100%","height":"100%","color":"","zIndex":0,"notRenderable":false,"isVisible":true,"descendantsOnlyPadding":false,"paddingLeft":"0px","paddingRight":"0px","paddingTop":"0px","paddingBottom":"0px","left":"0.5547581252463942px","top":"-0.9420582643294324px","linkOffsetX":"0px","linkOffsetY":"0px","isEnabled":true,"disabledColor":"#9a9a9a","disabledColorItem":"#6a6a6a","name":"EndButton_text","className":"TextBlock"}],"textBlockName":"EndButton_text"}],"columnCount":3,"rowCount":1,"columns":[{"value":0.33333333333333337,"unit":0},{"value":0.33333333333333337,"unit":0},{"value":0.33333333333333337,"unit":0}],"rows":[{"value":1,"unit":0}]},{"tags":["0:1"],"renderToIntermediateTexture":false,"maxLayoutCycle":3,"adaptHeightToChildren":false,"adaptWidthToChildren":false,"background":"","isHitTestVisible":true,"isPointerBlocker":true,"isFocusInvisible":false,"clipChildren":true,"clipContent":true,"useBitmapCache":false,"shadowOffsetX":0,"shadowOffsetY":0,"shadowBlur":0,"shadowColor":"black","hoverCursor":"","alpha":1,"scaleX":1,"scaleY":1,"rotation":0,"transformCenterY":0.5,"transformCenterX":0.5,"horizontalAlignment":2,"verticalAlignment":2,"fixedRatio":0,"width":"100%","height":"100%","color":"","zIndex":0,"notRenderable":false,"isVisible":true,"descendantsOnlyPadding":false,"paddingLeft":"0px","paddingRight":"0px","paddingTop":"0px","paddingBottom":"0px","left":"0px","top":"0px","linkOffsetX":"0px","linkOffsetY":"0px","isEnabled":true,"disabledColor":"#9a9a9a","disabledColorItem":"#6a6a6a","name":"Grid","className":"Grid","children":[{"tags":null,"thickness":1,"cornerRadius":0,"renderToIntermediateTexture":false,"maxLayoutCycle":3,"adaptHeightToChildren":false,"adaptWidthToChildren":false,"background":"#333333","isHitTestVisible":true,"isPointerBlocker":true,"isFocusInvisible":false,"clipChildren":true,"clipContent":true,"useBitmapCache":false,"shadowOffsetX":0,"shadowOffsetY":0,"shadowBlur":0,"shadowColor":"black","hoverCursor":"","fontOffset":{"ascent":90.5,"height":113.5,"descent":23},"alpha":1,"scaleX":1,"scaleY":1,"rotation":0,"transformCenterY":0.5,"transformCenterX":0.5,"horizontalAlignment":2,"verticalAlignment":2,"fixedRatio":0,"width":"644.76px","height":"131.19px","color":"#ffffff","zIndex":0,"notRenderable":false,"isVisible":true,"descendantsOnlyPadding":false,"paddingLeft":"0px","paddingRight":"0px","paddingTop":"0px","paddingBottom":"0px","left":"-2.11px","top":"45.23003605233081px","linkOffsetX":"0px","linkOffsetY":"0px","isEnabled":true,"disabledColor":"#9a9a9a","disabledColorItem":"#6a6a6a","name":"SettingButton","className":"Button","fontFamily":"Arial","fontSize":"100px","fontWeight":"","fontStyle":"","children":[{"tags":null,"resizeToFit":false,"textWrapping":1,"text":"Settings","textHorizontalAlignment":2,"textVerticalAlignment":2,"lineSpacing":"0px","outlineWidth":0,"underline":false,"lineThrough":false,"outlineColor":"white","wordDivider":" ","isHitTestVisible":true,"isPointerBlocker":false,"isFocusInvisible":false,"clipChildren":true,"clipContent":true,"useBitmapCache":false,"shadowOffsetX":0,"shadowOffsetY":0,"shadowBlur":0,"shadowColor":"black","hoverCursor":"","fontOffset":{"ascent":90.5,"height":113.5,"descent":23},"alpha":1,"scaleX":1,"scaleY":1,"rotation":0,"transformCenterY":0.5,"transformCenterX":0.5,"horizontalAlignment":2,"verticalAlignment":2,"fixedRatio":0,"width":"100%","height":"100%","color":"","zIndex":0,"notRenderable":false,"isVisible":true,"descendantsOnlyPadding":false,"paddingLeft":"0px","paddingRight":"0px","paddingTop":"0px","paddingBottom":"0px","left":"0px","top":"-0.3699639476691914px","linkOffsetX":"0px","linkOffsetY":"0px","isEnabled":true,"disabledColor":"#9a9a9a","disabledColorItem":"#6a6a6a","name":"SettingsButton_text","className":"TextBlock"}],"textBlockName":"SettingsButton_text"}],"columnCount":3,"rowCount":1,"columns":[{"value":0.33333333333333337,"unit":0},{"value":0.33333333333333337,"unit":0},{"value":0.33333333333333337,"unit":0}],"rows":[{"value":1,"unit":0}]},{"tags":["0:1"],"renderToIntermediateTexture":false,"maxLayoutCycle":3,"adaptHeightToChildren":false,"adaptWidthToChildren":false,"background":"","isHitTestVisible":true,"isPointerBlocker":true,"isFocusInvisible":false,"clipChildren":true,"clipContent":true,"useBitmapCache":false,"shadowOffsetX":0,"shadowOffsetY":0,"shadowBlur":0,"shadowColor":"black","hoverCursor":"","alpha":1,"scaleX":1,"scaleY":1,"rotation":0,"transformCenterY":0.5,"transformCenterX":0.5,"horizontalAlignment":2,"verticalAlignment":2,"fixedRatio":0,"width":"100%","height":"100%","color":"","zIndex":0,"notRenderable":false,"isVisible":true,"descendantsOnlyPadding":false,"paddingLeft":"0px","paddingRight":"0px","paddingTop":"0px","paddingBottom":"0px","left":"0px","top":"0px","linkOffsetX":"0px","linkOffsetY":"0px","isEnabled":true,"disabledColor":"#9a9a9a","disabledColorItem":"#6a6a6a","name":"Grid","className":"Grid","children":[{"tags":null,"thickness":1,"cornerRadius":0,"renderToIntermediateTexture":false,"maxLayoutCycle":3,"adaptHeightToChildren":false,"adaptWidthToChildren":false,"background":"#333333","isHitTestVisible":true,"isPointerBlocker":true,"isFocusInvisible":false,"clipChildren":true,"clipContent":true,"useBitmapCache":false,"shadowOffsetX":0,"shadowOffsetY":0,"shadowBlur":0,"shadowColor":"black","hoverCursor":"","fontOffset":{"ascent":90.5,"height":113.5,"descent":23},"alpha":1,"scaleX":1,"scaleY":1,"rotation":0,"transformCenterY":0.5,"transformCenterX":0.5,"horizontalAlignment":2,"verticalAlignment":2,"fixedRatio":0,"width":"644.76px","height":"131.19px","color":"#ffffff","zIndex":0,"notRenderable":false,"isVisible":true,"descendantsOnlyPadding":false,"paddingLeft":"0px","paddingRight":"0px","paddingTop":"0px","paddingBottom":"0px","left":"-2.11px","top":"45.23003605233081px","linkOffsetX":"0px","linkOffsetY":"0px","isEnabled":true,"disabledColor":"#9a9a9a","disabledColorItem":"#6a6a6a","name":"StartButton","className":"Button","fontFamily":"Arial","fontSize":"100px","fontWeight":"","fontStyle":"","children":[{"tags":null,"resizeToFit":false,"textWrapping":1,"text":"Start","textHorizontalAlignment":2,"textVerticalAlignment":2,"lineSpacing":"0px","outlineWidth":0,"underline":false,"lineThrough":false,"outlineColor":"white","wordDivider":" ","isHitTestVisible":true,"isPointerBlocker":false,"isFocusInvisible":false,"clipChildren":true,"clipContent":true,"useBitmapCache":false,"shadowOffsetX":0,"shadowOffsetY":0,"shadowBlur":0,"shadowColor":"black","hoverCursor":"","fontOffset":{"ascent":90.5,"height":113.5,"descent":23},"alpha":1,"scaleX":1,"scaleY":1,"rotation":0,"transformCenterY":0.5,"transformCenterX":0.5,"horizontalAlignment":2,"verticalAlignment":2,"fixedRatio":0,"width":"100%","height":"100%","color":"","zIndex":0,"notRenderable":false,"isVisible":true,"descendantsOnlyPadding":false,"paddingLeft":"0px","paddingRight":"0px","paddingTop":"0px","paddingBottom":"0px","left":"0px","top":"-0.3699639476691914px","linkOffsetX":"0px","linkOffsetY":"0px","isEnabled":true,"disabledColor":"#9a9a9a","disabledColorItem":"#6a6a6a","name":"StartButton_text","className":"TextBlock"}],"textBlockName":"StartButton_text"}],"columnCount":3,"rowCount":1,"columns":[{"value":0.33333333333333337,"unit":0},{"value":0.33333333333333337,"unit":0},{"value":0.33333333333333337,"unit":0}],"rows":[{"value":1,"unit":0}]}],"columnCount":1,"rowCount":3,"columns":[{"value":1,"unit":0}],"rows":[{"value":0.33333333333333337,"unit":0},{"value":0.33333333333333337,"unit":0},{"value":0.33333333333333337,"unit":0}]},{"tags":null,"resizeToFit":true,"textWrapping":0,"text":"The Dual Fight","textHorizontalAlignment":2,"textVerticalAlignment":2,"lineSpacing":"0px","outlineWidth":0,"underline":false,"lineThrough":false,"outlineColor":"#AAA6A6FF","wordDivider":" ","isHitTestVisible":true,"isPointerBlocker":true,"isFocusInvisible":false,"clipChildren":true,"clipContent":true,"useBitmapCache":false,"shadowOffsetX":0,"shadowOffsetY":0,"shadowBlur":0,"shadowColor":"black","hoverCursor":"","fontOffset":{"ascent":181,"height":227,"descent":46},"alpha":1,"scaleX":1,"scaleY":1,"rotation":0,"transformCenterY":0.5,"transformCenterX":0.5,"horizontalAlignment":2,"verticalAlignment":2,"fixedRatio":0,"width":"1314px","height":"227px","color":"#AEB0B3FF","zIndex":0,"notRenderable":false,"isVisible":true,"descendantsOnlyPadding":false,"paddingLeft":"0px","paddingRight":"0px","paddingTop":"0px","paddingBottom":"0px","left":"0px","top":"0px","linkOffsetX":"0px","linkOffsetY":"0px","isEnabled":true,"disabledColor":"#9a9a9a","disabledColorItem":"#6a6a6a","name":"GameTitleText","className":"TextBlock","fontFamily":"Arial","fontSize":"180px","fontWeight":"","fontStyle":""}],"columnCount":1,"rowCount":2,"columns":[{"value":1,"unit":0}],"rows":[{"value":0.39759036144578314,"unit":0},{"value":0.6024096385542168,"unit":0}]}]},"width":1920,"height":1080}